[
    {
      "name": "Brendan Rottmund",
      "about": [
        "I like food trucks and Greek!"
      ],
      "Restaraunt": [
        "Geno's Steaks",
        "Elia Greek Restaurant",
        "E Mei Restaurant",
        "salam-cafe-and-market-philadelphia",
        "Jay's Steak & Hoagie Joint"
      ],
      "match": [
        "Steve Fokas",
        "Joshua Harris"
      ]
    },
    
    {
      "name": "Steve Fokas",
      "Restaraunt": [
        "Geno's Steaks",
        "SPOT Gourmet Burgers",
        "Taqueria La Herradura",
        "Di Bruno Bros.",
        "Van Leeuwen Ice Cream"
      ],
      "match": [
        "Brendan Rottmund",
        "Kimberly Perez"
      ]
    },
    
    {
      "name": "Kimberly Perez",
      "Restaraunt": [
        "SPOT Gourmet Burgers",
        "Johnny's Hots",
        "Somerset Splits",
        "Thanal Indian Tavern",
        "MoonDog Grill"
      ],
      "match": [
        "Steve Fokas",
        "Joshua Harris"
      ]
    },

    {
      "name": "Joshua harris",
      "Restaraunt": [
        "Emei",
        "Johnny's Hots",
        "Sweets & Curry House",
        "Reading Terminal Market",
        "Vista Peru"
      ],
      "match": [
        "Brendan Rottmund",
        "Kimberly Perez"
      ]
    }

  ]
  